installer/__init__.py
installer/installer.py
installer/version_checker.py
netskope_log_stream_client_installer-1.0.11.dist-info/licenses/LICENSE
netskope_log_stream_client_installer-1.0.11.dist-info/METADATA
netskope_log_stream_client_installer-1.0.11.dist-info/WHEEL
netskope_log_stream_client_installer-1.0.11.dist-info/entry_points.txt
netskope_log_stream_client_installer-1.0.11.dist-info/top_level.txt
netskope_log_stream_client_installer-1.0.11.dist-info/RECORD
