Metadata-Version: 2.4
Name: netskope-log-stream-client-installer
Version: 1.0.11
Summary: Netskope Log Stream Client Installer
Author-email: Netskope <support@netskope.com>
License-Expression: MIT
Project-URL: Homepage, https://github.com/netskope/log-stream-client
Project-URL: Issues, https://github.com/netskope/log-stream-client/issues
Classifier: Development Status :: 4 - Beta
Classifier: Intended Audience :: System Administrators
Classifier: Operating System :: POSIX :: Linux
Classifier: Programming Language :: Python :: 3
Classifier: Programming Language :: Python :: 3.7
Classifier: Programming Language :: Python :: 3.8
Classifier: Programming Language :: Python :: 3.9
Classifier: Programming Language :: Python :: 3.10
Classifier: Programming Language :: Python :: 3.11
Requires-Python: >=3.7
License-File: LICENSE
Requires-Dist: requests>=2.25.0
Requires-Dist: packaging>=20.0
Dynamic: license-file
